openm3u8-7.1.0.dist-info/RECORD
openm3u8-7.1.0.dist-info/WHEEL
openm3u8-7.1.0.dist-info/top_level.txt
openm3u8-7.1.0.dist-info/METADATA
openm3u8-7.1.0.dist-info/licenses/LICENSE
openm3u8/mixins.py
openm3u8/httpclient.py
openm3u8/_m3u8_parser.c
openm3u8/version_matching.py
openm3u8/protocol.py
openm3u8/__init__.py
openm3u8/model.py
openm3u8/parser.py
openm3u8/_m3u8_parser.abi3.so
openm3u8/version_matching_rules.py
