Metadata-Version: 2.4
Name: openm3u8
Version: 7.1.0
Summary: Python m3u8 parser
Author: wurl.com
License: MIT
Project-URL: Homepage, https://github.com/openwurl/openm3u8
Project-URL: Repository, https://github.com/openwurl/openm3u8
Classifier: Development Status :: 5 - Production/Stable
Classifier: Intended Audience :: Developers
Classifier: Operating System :: OS Independent
Classifier: Programming Language :: Python :: 3
Requires-Python: >=3.10
License-File: LICENSE
Requires-Dist: backports-datetime-fromisoformat; python_version < "3.11"
Provides-Extra: dev
Requires-Dist: bottle; extra == "dev"
Requires-Dist: pytest>=9.0.1; extra == "dev"
Requires-Dist: pytest-cov>=7.0.0; extra == "dev"
Dynamic: license-file
